luxos/__init__.py
luxos/__main__.py
luxos/api.json
luxos/api.py
luxos/asyncops.py
luxos/exceptions.py
luxos/ips.py
luxos/misc.py
luxos/py.typed
luxos/syncops.py
luxos/text.py
luxos/utils.py
luxos/version.py
luxos/cli/__init__.py
luxos/cli/flags.py
luxos/cli/shared.py
luxos/cli/v1.py
luxos/scripts/__init__.py
luxos/scripts/async_luxos.py
luxos/scripts/health_checker.py
luxos/scripts/luxos.py
luxos/scripts/luxos_run.py
luxos-0.2.4.dist-info/METADATA
luxos-0.2.4.dist-info/WHEEL
luxos-0.2.4.dist-info/entry_points.txt
luxos-0.2.4.dist-info/top_level.txt
luxos-0.2.4.dist-info/RECORD
