Metadata-Version: 2.1
Name: luxos
Version: 0.2.4
Summary: The all encompassing LuxOS python library.
Author-email: Antonio Cavallo <antonio.cavallo@luxor.tech>
License: MIT
Project-URL: Source, https://github.com/LuxorLabs/firmware-biz-tools
Project-URL: Issues, https://github.com/LuxorLabs/firmware-biz-tools/issues
Project-URL: Documentation, https://luxorlabs.github.io/luxos-tooling
Classifier: Development Status :: 4 - Beta
Classifier: Programming Language :: Python
Classifier: Programming Language :: Python :: 3.8
Classifier: Programming Language :: Python :: 3.9
Classifier: Programming Language :: Python :: 3.10
Classifier: Programming Language :: Python :: 3.11
Classifier: Programming Language :: Python :: 3.12
Classifier: Programming Language :: Python :: 3.13
Requires-Python: >=3.9
Requires-Dist: pyyaml
Provides-Extra: extra
Requires-Dist: asyncpg ; extra == 'extra'
Requires-Dist: httpx ; extra == 'extra'
Requires-Dist: pandas ; extra == 'extra'
Requires-Dist: tqdm ; extra == 'extra'
